README.md
setup.cfg
setup.py
skypond/__init__.py
skypond.egg-info/PKG-INFO
skypond.egg-info/SOURCES.txt
skypond.egg-info/dependency_links.txt
skypond.egg-info/requires.txt
skypond.egg-info/top_level.txt
skypond/games/__init__.py
skypond/games/base/__init__.py
skypond/games/base/agent_http_proxy.py
skypond/games/base/base_agent.py
skypond/games/base/callback_agent.py
skypond/games/base/multi_agent_coordinator.py
skypond/games/base/shared_state.py
skypond/games/four_keys/__init__.py
skypond/games/four_keys/four_keys_actions.py
skypond/games/four_keys/four_keys_board_items.py
skypond/games/four_keys/four_keys_constants.py
skypond/games/four_keys/four_keys_environment.py
skypond/games/four_keys/four_keys_shared_state.py
skypond/games/four_keys/agents/__init__.py
skypond/games/four_keys/agents/random_accumulating_agent.py
skypond/games/four_keys/agents/random_agent.py