Metadata-Version: 2.1
Name: skypond
Version: 0.2.0
Summary: A simple reinforcement learning competition foundation
Home-page: https://github.com/upkoi/skypond
Author: Rob Venables
Author-email: rob@upkoi.com
License: MIT
Platform: UNKNOWN
Classifier: Development Status :: 3 - Alpha
Classifier: Intended Audience :: Developers
Classifier: Intended Audience :: Education
Classifier: Intended Audience :: Science/Research
Classifier: License :: OSI Approved :: MIT License
Classifier: Programming Language :: Python :: 3
Classifier: Programming Language :: Python :: 3.6
Classifier: Topic :: Software Development :: Libraries
Classifier: Topic :: Software Development :: Libraries :: Python Modules
Provides-Extra: tests
